glovo_mlp_feature_store_operators/__init__.py
glovo_mlp_feature_store_operators-0.0.0.dist-info/METADATA
glovo_mlp_feature_store_operators-0.0.0.dist-info/WHEEL
glovo_mlp_feature_store_operators-0.0.0.dist-info/top_level.txt
glovo_mlp_feature_store_operators-0.0.0.dist-info/RECORD
